atlassian_statuspage/__init__.py
atlassian_statuspage/api_client.py
atlassian_statuspage/configuration.py
atlassian_statuspage/rest.py
atlassian_statuspage/api/__init__.py
atlassian_statuspage/api/component_groups_api.py
atlassian_statuspage/api/components_api.py
atlassian_statuspage/api/incident_postmortem_api.py
atlassian_statuspage/api/incident_subscribers_api.py
atlassian_statuspage/api/incident_updates_api.py
atlassian_statuspage/api/incidents_api.py
atlassian_statuspage/api/metric_providers_api.py
atlassian_statuspage/api/metrics_api.py
atlassian_statuspage/api/page_access_group_components_api.py
atlassian_statuspage/api/page_access_groups_api.py
atlassian_statuspage/api/page_access_user_components_api.py
atlassian_statuspage/api/page_access_user_metrics_api.py
atlassian_statuspage/api/page_access_users_api.py
atlassian_statuspage/api/pages_api.py
atlassian_statuspage/api/permissions_api.py
atlassian_statuspage/api/status_embed_config_api.py
atlassian_statuspage/api/subscribers_api.py
atlassian_statuspage/api/templates_api.py
atlassian_statuspage/api/users_api.py
atlassian_statuspage/models/__init__.py
atlassian_statuspage/models/component.py
atlassian_statuspage/models/component_group_uptime.py
atlassian_statuspage/models/component_group_uptime_related_events.py
atlassian_statuspage/models/component_id_page_access_users_body.py
atlassian_statuspage/models/component_uptime.py
atlassian_statuspage/models/component_uptime_related_events.py
atlassian_statuspage/models/delete_pages_page_id_page_access_groups_page_access_group_id_components.py
atlassian_statuspage/models/delete_pages_page_id_page_access_users_page_access_user_id_components.py
atlassian_statuspage/models/delete_pages_page_id_page_access_users_page_access_user_id_metrics.py
atlassian_statuspage/models/error_entity.py
atlassian_statuspage/models/group_component.py
atlassian_statuspage/models/incident.py
atlassian_statuspage/models/incident_template.py
atlassian_statuspage/models/incident_update.py
atlassian_statuspage-1.0.2.dist-info/WHEEL
atlassian_statuspage-1.0.2.dist-info/METADATA
atlassian_statuspage-1.0.2.dist-info/RECORD
