Metadata-Version: 2.3
Name: atlassian_statuspage
Version: 1.0.2
Summary: Statuspage.io API Client
Author-email: Kishore Kumar <spkishore007@gmail.com>
Requires-Python: >=3.7
Requires-Dist: urllib3 == 1.26.16
Requires-Dist: six == 1.16.0
Requires-Dist: certifi == 2023.5.7
Requires-Dist: python_dateutil == 2.8.2
Requires-Dist: requests == 2.29.0
Requires-Dist: lambda_thread_pool == 0.0.2
Requires-Dist: pylint ~=2.14.0 ; extra == "dev"
Requires-Dist: toml ~=0.10.2 ; extra == "dev"
Requires-Dist: yapf ~=0.32.0 ; extra == "dev"
Requires-Dist: coverage >= 4.0.3 ; extra == "tests"
Requires-Dist: nose >= 1.3.7 ; extra == "tests"
Requires-Dist: pluggy >= 0.3.1 ; extra == "tests"
Requires-Dist: py >= 1.4.31 ; extra == "tests"
Requires-Dist: randomize >= 0.13 ; extra == "tests"
Provides-Extra: dev
Provides-Extra: tests
